{
    "peliculas": [
        {
            "id": 1,
            "caratula" : "https://pics.filmaffinity.com/citizen_kane-217208961-large.jpg",
            "nombre" : "Ciudadano Kane",
            "director" : "Orson Welles",
            "clasification" : "Drama"
        },
        {   
            "id": 2,
            "caratula" : "https://pics.filmaffinity.com/the_bridges_of_madison_county-998728421-large.jpg",
            "nombre" : "Los puentes de Madison",
            "director" : "Clint Eastwood",
            "clasification" : "Romance. Drama"
        },
        {   
            "id": 3,
            "caratula" : "",
            "nombre" : "",
            "director" : "",
            "clasification" : ""
        },
        {   
            "id": 4,
            "caratula" : "",
            "nombre" : "",
            "director" : "",
            "clasification" : ""
        },
        {   
            "id": 5,
            "caratula" : "",
            "nombre" : "",
            "director" : "",
            "clasification" : ""
        },
        {   
            "id": 6,
            "caratula" : "",
            "nombre" : "",
            "director" : "",
            "clasification" : ""
        },
        {   
            "id": 7,
            "caratula" : "",
            "nombre" : "",
            "director" : "",
            "clasification" : ""
        },
        {   
            "id": 8,
            "caratula" : "",
            "nombre" : "",
            "director" : "",
            "clasification" : ""
        },
        {   
            "id": 9,
            "caratula" : "",
            "nombre" : "",
            "director" : "",
            "clasification" : ""
        },
        {   
            "id": 10,
            "caratula" : "",
            "nombre" : "",
            "director" : "",
            "clasification" : ""
        }
    ]
}